dapla/__init__.py
dapla/backports.py
dapla/collector.py
dapla/const.py
dapla/converter.py
dapla/doctor.py
dapla/files.py
dapla/gcs.py
dapla/git.py
dapla/gsm.py
dapla/guardian.py
dapla/pandas.py
dapla/pubsub.py
dapla/py.typed
dapla/spark/__init__.py
dapla/spark/sparkui.py
dapla_toolbelt-4.0.1.dist-info/LICENSE
dapla_toolbelt-4.0.1.dist-info/METADATA
dapla_toolbelt-4.0.1.dist-info/WHEEL
dapla_toolbelt-4.0.1.dist-info/RECORD
