Metadata-Version: 2.1
Name: dapla-toolbelt
Version: 4.0.1
Summary: Dapla Toolbelt
Home-page: https://github.com/statisticsnorway/dapla-toolbelt
License: MIT
Author: Dapla Developers
Author-email: dapla-platform-developers@ssb.no
Requires-Python: >=3.10,<4.0
Classifier: Development Status :: 5 - Production/Stable
Classifier: License :: OSI Approved :: MIT License
Classifier: Programming Language :: Python :: 3
Classifier: Programming Language :: Python :: 3.10
Classifier: Programming Language :: Python :: 3.11
Classifier: Programming Language :: Python :: 3.12
Requires-Dist: dapla-auth-client (>=1.0.1)
Requires-Dist: deprecated (>=1.2.18,<2.0.0)
Requires-Dist: fsspec (>=2023.12.2)
Requires-Dist: gcsfs (>=2022.7.1)
Requires-Dist: google-cloud-pubsub (>=2.14.1)
Requires-Dist: google-cloud-secret-manager (>=2.21.0)
Requires-Dist: google-cloud-storage (>=2.7.0)
Requires-Dist: pandas[excel,xml] (>=1.4.2)
Requires-Dist: pyarrow (>=14.0.2)
Requires-Dist: pyjwt (>=2.6.0)
Requires-Dist: requests (>=2.27.1)
Requires-Dist: tomli (>=1.1.0)
Requires-Dist: types-deprecated (>=1.2.15.20250304,<2.0.0.0)
Project-URL: Changelog, https://github.com/statisticsnorway/dapla-toolbelt/releases
Project-URL: Documentation, https://statisticsnorway.github.io/dapla-toolbelt
Project-URL: Repository, https://github.com/statisticsnorway/dapla-toolbelt
